flake8_empty_init_modules.py
flake8_empty_init_modules-1.0.1.dist-info/LICENSE
flake8_empty_init_modules-1.0.1.dist-info/METADATA
flake8_empty_init_modules-1.0.1.dist-info/WHEEL
flake8_empty_init_modules-1.0.1.dist-info/entry_points.txt
flake8_empty_init_modules-1.0.1.dist-info/top_level.txt
flake8_empty_init_modules-1.0.1.dist-info/RECORD
