Metadata-Version: 2.1
Name: flake8-empty-init-modules
Version: 1.0.1
Summary: flake8 plugin that checks for code in `__init__.py` modules
Home-page: https://github.com/samueljsb/flake8-empty-init-modules
Author: Samuel Searles-Bryant
Author-email: sam@samueljsb.co.uk
License: MIT
Classifier: License :: OSI Approved :: MIT License
Classifier: Programming Language :: Python :: 3
Classifier: Programming Language :: Python :: 3 :: Only
Classifier: Programming Language :: Python :: Implementation :: CPython
Requires-Python: >=3.8
License-File: LICENSE
Requires-Dist: flake8 (>=4)
